my_library/__init__.py
edik_my_library-0.1.1.dist-info/METADATA
edik_my_library-0.1.1.dist-info/WHEEL
edik_my_library-0.1.1.dist-info/top_level.txt
edik_my_library-0.1.1.dist-info/RECORD
