Metadata-Version: 2.4
Name: edik-my-library
Version: 0.1.1
Summary: Bu mənim ilk PyPI kitabxanam
Home-page: https://github.com/username/my_library
Author: Sənin adın
Author-email: email@example.com
Classifier: Programming Language :: Python :: 3
Classifier: License :: OSI Approved :: MIT License
Classifier: Operating System :: OS Independent
Requires-Python: >=3.8
Dynamic: author
Dynamic: author-email
Dynamic: classifier
Dynamic: description-content-type
Dynamic: home-page
Dynamic: requires-python
Dynamic: summary
